{
  "inputs": {
    "../core/src/types/ConfigNode.ts": {
      "bytes": 2239,
      "imports": [],
      "format": "esm"
    },
    "../core/src/types/IRule.ts": {
      "bytes": 5005,
      "imports": [
        {
          "path": "../core/src/types/ConfigNode.ts",
          "kind": "import-statement",
          "original": "./ConfigNode"
        }
      ],
      "format": "esm"
    },
    "../core/src/parser/VendorSchema.ts": {
      "bytes": 2301,
      "imports": [],
      "format": "esm"
    },
    "../core/src/parser/vendors/cisco-ios.ts": {
      "bytes": 3698,
      "imports": [
        {
          "path": "../core/src/parser/VendorSchema.ts",
          "kind": "import-statement",
          "original": "../VendorSchema"
        }
      ],
      "format": "esm"
    },
    "../core/src/parser/vendors/cisco-nxos.ts": {
      "bytes": 3334,
      "imports": [
        {
          "path": "../core/src/parser/VendorSchema.ts",
          "kind": "import-statement",
          "original": "../VendorSchema"
        }
      ],
      "format": "esm"
    },
    "../core/src/parser/vendors/juniper-junos.ts": {
      "bytes": 7681,
      "imports": [
        {
          "path": "../core/src/parser/VendorSchema.ts",
          "kind": "import-statement",
          "original": "../VendorSchema"
        }
      ],
      "format": "esm"
    },
    "../core/src/parser/vendors/aruba-aoscx.ts": {
      "bytes": 3675,
      "imports": [
        {
          "path": "../core/src/parser/VendorSchema.ts",
          "kind": "import-statement",
          "original": "../VendorSchema"
        }
      ],
      "format": "esm"
    },
    "../core/src/parser/vendors/aruba-aosswitch.ts": {
      "bytes": 3329,
      "imports": [
        {
          "path": "../core/src/parser/VendorSchema.ts",
          "kind": "import-statement",
          "original": "../VendorSchema"
        }
      ],
      "format": "esm"
    },
    "../core/src/parser/vendors/aruba-wlc.ts": {
      "bytes": 6287,
      "imports": [
        {
          "path": "../core/src/parser/VendorSchema.ts",
          "kind": "import-statement",
          "original": "../VendorSchema"
        }
      ],
      "format": "esm"
    },
    "../core/src/parser/vendors/index.ts": {
      "bytes": 8500,
      "imports": [
        {
          "path": "../core/src/parser/VendorSchema.ts",
          "kind": "import-statement",
          "original": "../VendorSchema"
        },
        {
          "path": "../core/src/parser/vendors/cisco-ios.ts",
          "kind": "import-statement",
          "original": "./cisco-ios"
        },
        {
          "path": "../core/src/parser/vendors/cisco-nxos.ts",
          "kind": "import-statement",
          "original": "./cisco-nxos"
        },
        {
          "path": "../core/src/parser/vendors/juniper-junos.ts",
          "kind": "import-statement",
          "original": "./juniper-junos"
        },
        {
          "path": "../core/src/parser/vendors/aruba-aoscx.ts",
          "kind": "import-statement",
          "original": "./aruba-aoscx"
        },
        {
          "path": "../core/src/parser/vendors/aruba-aosswitch.ts",
          "kind": "import-statement",
          "original": "./aruba-aosswitch"
        },
        {
          "path": "../core/src/parser/vendors/aruba-wlc.ts",
          "kind": "import-statement",
          "original": "./aruba-wlc"
        },
        {
          "path": "../core/src/parser/vendors/cisco-ios.ts",
          "kind": "import-statement",
          "original": "./cisco-ios"
        },
        {
          "path": "../core/src/parser/vendors/cisco-nxos.ts",
          "kind": "import-statement",
          "original": "./cisco-nxos"
        },
        {
          "path": "../core/src/parser/vendors/juniper-junos.ts",
          "kind": "import-statement",
          "original": "./juniper-junos"
        },
        {
          "path": "../core/src/parser/vendors/aruba-aoscx.ts",
          "kind": "import-statement",
          "original": "./aruba-aoscx"
        },
        {
          "path": "../core/src/parser/vendors/aruba-aosswitch.ts",
          "kind": "import-statement",
          "original": "./aruba-aosswitch"
        },
        {
          "path": "../core/src/parser/vendors/aruba-wlc.ts",
          "kind": "import-statement",
          "original": "./aruba-wlc"
        }
      ],
      "format": "esm"
    },
    "../core/src/parser/Sanitizer.ts": {
      "bytes": 3146,
      "imports": [],
      "format": "esm"
    },
    "../core/src/constants.ts": {
      "bytes": 1839,
      "imports": [],
      "format": "esm"
    },
    "../core/src/errors.ts": {
      "bytes": 2463,
      "imports": [],
      "format": "esm"
    },
    "../core/src/parser/SchemaAwareParser.ts": {
      "bytes": 12375,
      "imports": [
        {
          "path": "../core/src/types/ConfigNode.ts",
          "kind": "import-statement",
          "original": "../types/ConfigNode"
        },
        {
          "path": "../core/src/parser/VendorSchema.ts",
          "kind": "import-statement",
          "original": "./VendorSchema"
        },
        {
          "path": "../core/src/parser/vendors/index.ts",
          "kind": "import-statement",
          "original": "./vendors"
        },
        {
          "path": "../core/src/parser/Sanitizer.ts",
          "kind": "import-statement",
          "original": "./Sanitizer"
        },
        {
          "path": "../core/src/constants.ts",
          "kind": "import-statement",
          "original": "../constants"
        },
        {
          "path": "../core/src/errors.ts",
          "kind": "import-statement",
          "original": "../errors"
        }
      ],
      "format": "esm"
    },
    "../core/src/parser/IncrementalParser.ts": {
      "bytes": 16062,
      "imports": [
        {
          "path": "../core/src/types/ConfigNode.ts",
          "kind": "import-statement",
          "original": "../types/ConfigNode"
        },
        {
          "path": "../core/src/parser/SchemaAwareParser.ts",
          "kind": "import-statement",
          "original": "./SchemaAwareParser"
        },
        {
          "path": "../core/src/parser/VendorSchema.ts",
          "kind": "import-statement",
          "original": "./VendorSchema"
        },
        {
          "path": "../core/src/parser/vendors/index.ts",
          "kind": "import-statement",
          "original": "./vendors"
        },
        {
          "path": "../core/src/constants.ts",
          "kind": "import-statement",
          "original": "../constants"
        }
      ],
      "format": "esm"
    },
    "../core/src/engine/RuleExecutor.ts": {
      "bytes": 7200,
      "imports": [
        {
          "path": "../core/src/types/ConfigNode.ts",
          "kind": "import-statement",
          "original": "../types/ConfigNode"
        },
        {
          "path": "../core/src/types/IRule.ts",
          "kind": "import-statement",
          "original": "../types/IRule"
        },
        {
          "path": "../core/src/constants.ts",
          "kind": "import-statement",
          "original": "../constants"
        }
      ],
      "format": "esm"
    },
    "../core/src/engine/Runner.ts": {
      "bytes": 8938,
      "imports": [
        {
          "path": "../core/src/types/ConfigNode.ts",
          "kind": "import-statement",
          "original": "../types/ConfigNode"
        },
        {
          "path": "../core/src/types/IRule.ts",
          "kind": "import-statement",
          "original": "../types/IRule"
        },
        {
          "path": "../core/src/engine/RuleExecutor.ts",
          "kind": "import-statement",
          "original": "./RuleExecutor"
        }
      ],
      "format": "esm"
    },
    "../core/src/index.ts": {
      "bytes": 422,
      "imports": [
        {
          "path": "../core/src/types/ConfigNode.ts",
          "kind": "import-statement",
          "original": "./types/ConfigNode"
        },
        {
          "path": "../core/src/types/IRule.ts",
          "kind": "import-statement",
          "original": "./types/IRule"
        },
        {
          "path": "../core/src/parser/SchemaAwareParser.ts",
          "kind": "import-statement",
          "original": "./parser/SchemaAwareParser"
        },
        {
          "path": "../core/src/parser/IncrementalParser.ts",
          "kind": "import-statement",
          "original": "./parser/IncrementalParser"
        },
        {
          "path": "../core/src/parser/VendorSchema.ts",
          "kind": "import-statement",
          "original": "./parser/VendorSchema"
        },
        {
          "path": "../core/src/parser/vendors/index.ts",
          "kind": "import-statement",
          "original": "./parser/vendors"
        },
        {
          "path": "../core/src/engine/Runner.ts",
          "kind": "import-statement",
          "original": "./engine/Runner"
        },
        {
          "path": "../core/src/engine/RuleExecutor.ts",
          "kind": "import-statement",
          "original": "./engine/RuleExecutor"
        },
        {
          "path": "../core/src/parser/Sanitizer.ts",
          "kind": "import-statement",
          "original": "./parser/Sanitizer"
        },
        {
          "path": "../core/src/constants.ts",
          "kind": "import-statement",
          "original": "./constants"
        },
        {
          "path": "../core/src/errors.ts",
          "kind": "import-statement",
          "original": "./errors"
        }
      ],
      "format": "esm"
    },
    "../rules-default/src/common/helpers.ts": {
      "bytes": 5194,
      "imports": [
        {
          "path": "../core/src/index.ts",
          "kind": "import-statement",
          "original": "@sentriflow/core"
        }
      ],
      "format": "esm"
    },
    "../rules-default/src/common/network-rules.ts": {
      "bytes": 13293,
      "imports": [
        {
          "path": "../core/src/index.ts",
          "kind": "import-statement",
          "original": "@sentriflow/core"
        },
        {
          "path": "../rules-default/src/common/helpers.ts",
          "kind": "import-statement",
          "original": "./helpers"
        }
      ],
      "format": "esm"
    },
    "../rules-default/src/common/index.ts": {
      "bytes": 173,
      "imports": [
        {
          "path": "../rules-default/src/common/network-rules.ts",
          "kind": "import-statement",
          "original": "./network-rules"
        },
        {
          "path": "../rules-default/src/common/helpers.ts",
          "kind": "import-statement",
          "original": "./helpers"
        }
      ],
      "format": "esm"
    },
    "../rules-default/src/cisco/helpers.ts": {
      "bytes": 4939,
      "imports": [
        {
          "path": "../core/src/index.ts",
          "kind": "import-statement",
          "original": "@sentriflow/core"
        },
        {
          "path": "../rules-default/src/common/helpers.ts",
          "kind": "import-statement",
          "original": "../common/helpers"
        },
        {
          "path": "../rules-default/src/common/helpers.ts",
          "kind": "import-statement",
          "original": "../common/helpers"
        }
      ],
      "format": "esm"
    },
    "../rules-default/src/cisco/ios-rules.ts": {
      "bytes": 37824,
      "imports": [
        {
          "path": "../core/src/index.ts",
          "kind": "import-statement",
          "original": "@sentriflow/core"
        },
        {
          "path": "../rules-default/src/common/helpers.ts",
          "kind": "import-statement",
          "original": "../common/helpers"
        },
        {
          "path": "../rules-default/src/cisco/helpers.ts",
          "kind": "import-statement",
          "original": "./helpers"
        }
      ],
      "format": "esm"
    },
    "../rules-default/src/cisco/index.ts": {
      "bytes": 148,
      "imports": [
        {
          "path": "../rules-default/src/cisco/ios-rules.ts",
          "kind": "import-statement",
          "original": "./ios-rules"
        },
        {
          "path": "../rules-default/src/cisco/helpers.ts",
          "kind": "import-statement",
          "original": "./helpers"
        }
      ],
      "format": "esm"
    },
    "../rules-default/src/juniper/helpers.ts": {
      "bytes": 5390,
      "imports": [
        {
          "path": "../core/src/index.ts",
          "kind": "import-statement",
          "original": "@sentriflow/core"
        },
        {
          "path": "../rules-default/src/common/helpers.ts",
          "kind": "import-statement",
          "original": "../common/helpers"
        },
        {
          "path": "../rules-default/src/common/helpers.ts",
          "kind": "import-statement",
          "original": "../common/helpers"
        }
      ],
      "format": "esm"
    },
    "../rules-default/src/juniper/junos-rules.ts": {
      "bytes": 19677,
      "imports": [
        {
          "path": "../core/src/index.ts",
          "kind": "import-statement",
          "original": "@sentriflow/core"
        },
        {
          "path": "../rules-default/src/juniper/helpers.ts",
          "kind": "import-statement",
          "original": "./helpers"
        }
      ],
      "format": "esm"
    },
    "../rules-default/src/juniper/index.ts": {
      "bytes": 143,
      "imports": [
        {
          "path": "../rules-default/src/juniper/junos-rules.ts",
          "kind": "import-statement",
          "original": "./junos-rules"
        },
        {
          "path": "../rules-default/src/juniper/helpers.ts",
          "kind": "import-statement",
          "original": "./helpers"
        }
      ],
      "format": "esm"
    },
    "../rules-default/src/aruba/helpers.ts": {
      "bytes": 13729,
      "imports": [
        {
          "path": "../core/src/index.ts",
          "kind": "import-statement",
          "original": "@sentriflow/core"
        },
        {
          "path": "../rules-default/src/common/helpers.ts",
          "kind": "import-statement",
          "original": "../common/helpers"
        },
        {
          "path": "../rules-default/src/common/helpers.ts",
          "kind": "import-statement",
          "original": "../common/helpers"
        }
      ],
      "format": "esm"
    },
    "../rules-default/src/aruba/common-rules.ts": {
      "bytes": 11176,
      "imports": [
        {
          "path": "../core/src/index.ts",
          "kind": "import-statement",
          "original": "@sentriflow/core"
        },
        {
          "path": "../rules-default/src/aruba/helpers.ts",
          "kind": "import-statement",
          "original": "./helpers"
        }
      ],
      "format": "esm"
    },
    "../rules-default/src/aruba/aoscx-rules.ts": {
      "bytes": 16648,
      "imports": [
        {
          "path": "../core/src/index.ts",
          "kind": "import-statement",
          "original": "@sentriflow/core"
        },
        {
          "path": "../rules-default/src/aruba/helpers.ts",
          "kind": "import-statement",
          "original": "./helpers"
        }
      ],
      "format": "esm"
    },
    "../rules-default/src/aruba/aosswitch-rules.ts": {
      "bytes": 12473,
      "imports": [
        {
          "path": "../core/src/index.ts",
          "kind": "import-statement",
          "original": "@sentriflow/core"
        },
        {
          "path": "../rules-default/src/aruba/helpers.ts",
          "kind": "import-statement",
          "original": "./helpers"
        }
      ],
      "format": "esm"
    },
    "../rules-default/src/aruba/wlc-rules.ts": {
      "bytes": 15406,
      "imports": [
        {
          "path": "../core/src/index.ts",
          "kind": "import-statement",
          "original": "@sentriflow/core"
        },
        {
          "path": "../rules-default/src/aruba/helpers.ts",
          "kind": "import-statement",
          "original": "./helpers"
        }
      ],
      "format": "esm"
    },
    "../rules-default/src/aruba/index.ts": {
      "bytes": 2022,
      "imports": [
        {
          "path": "../rules-default/src/aruba/helpers.ts",
          "kind": "import-statement",
          "original": "./helpers"
        },
        {
          "path": "../rules-default/src/aruba/common-rules.ts",
          "kind": "import-statement",
          "original": "./common-rules"
        },
        {
          "path": "../rules-default/src/aruba/aoscx-rules.ts",
          "kind": "import-statement",
          "original": "./aoscx-rules"
        },
        {
          "path": "../rules-default/src/aruba/aosswitch-rules.ts",
          "kind": "import-statement",
          "original": "./aosswitch-rules"
        },
        {
          "path": "../rules-default/src/aruba/wlc-rules.ts",
          "kind": "import-statement",
          "original": "./wlc-rules"
        },
        {
          "path": "../core/src/index.ts",
          "kind": "import-statement",
          "original": "@sentriflow/core"
        },
        {
          "path": "../rules-default/src/aruba/common-rules.ts",
          "kind": "import-statement",
          "original": "./common-rules"
        },
        {
          "path": "../rules-default/src/aruba/aoscx-rules.ts",
          "kind": "import-statement",
          "original": "./aoscx-rules"
        },
        {
          "path": "../rules-default/src/aruba/aosswitch-rules.ts",
          "kind": "import-statement",
          "original": "./aosswitch-rules"
        },
        {
          "path": "../rules-default/src/aruba/wlc-rules.ts",
          "kind": "import-statement",
          "original": "./wlc-rules"
        }
      ],
      "format": "esm"
    },
    "../rules-default/src/index.ts": {
      "bytes": 2669,
      "imports": [
        {
          "path": "../core/src/index.ts",
          "kind": "import-statement",
          "original": "@sentriflow/core"
        },
        {
          "path": "../rules-default/src/common/index.ts",
          "kind": "import-statement",
          "original": "./common"
        },
        {
          "path": "../rules-default/src/cisco/index.ts",
          "kind": "import-statement",
          "original": "./cisco"
        },
        {
          "path": "../rules-default/src/juniper/index.ts",
          "kind": "import-statement",
          "original": "./juniper"
        },
        {
          "path": "../rules-default/src/aruba/index.ts",
          "kind": "import-statement",
          "original": "./aruba"
        },
        {
          "path": "../rules-default/src/common/network-rules.ts",
          "kind": "import-statement",
          "original": "./common/network-rules"
        },
        {
          "path": "../rules-default/src/cisco/ios-rules.ts",
          "kind": "import-statement",
          "original": "./cisco/ios-rules"
        },
        {
          "path": "../rules-default/src/juniper/junos-rules.ts",
          "kind": "import-statement",
          "original": "./juniper/junos-rules"
        },
        {
          "path": "../rules-default/src/aruba/index.ts",
          "kind": "import-statement",
          "original": "./aruba"
        },
        {
          "path": "../rules-default/src/common/network-rules.ts",
          "kind": "import-statement",
          "original": "./common/network-rules"
        },
        {
          "path": "../rules-default/src/cisco/ios-rules.ts",
          "kind": "import-statement",
          "original": "./cisco/ios-rules"
        },
        {
          "path": "../rules-default/src/cisco/ios-rules.ts",
          "kind": "import-statement",
          "original": "./cisco/ios-rules"
        }
      ],
      "format": "esm"
    },
    "src/extension.ts": {
      "bytes": 40268,
      "imports": [
        {
          "path": "vscode",
          "kind": "import-statement",
          "external": true
        },
        {
          "path": "../core/src/index.ts",
          "kind": "import-statement",
          "original": "@sentriflow/core"
        },
        {
          "path": "../rules-default/src/index.ts",
          "kind": "import-statement",
          "original": "@sentriflow/rules-default"
        }
      ],
      "format": "esm"
    }
  },
  "outputs": {
    "dist/extension.js": {
      "imports": [
        {
          "path": "vscode",
          "kind": "require-call",
          "external": true
        }
      ],
      "exports": [],
      "entryPoint": "src/extension.ts",
      "inputs": {
        "src/extension.ts": {
          "bytesInOutput": 13016
        },
        "../core/src/index.ts": {
          "bytesInOutput": 0
        },
        "../core/src/parser/vendors/cisco-ios.ts": {
          "bytesInOutput": 2065
        },
        "../core/src/parser/vendors/cisco-nxos.ts": {
          "bytesInOutput": 1461
        },
        "../core/src/parser/vendors/juniper-junos.ts": {
          "bytesInOutput": 3513
        },
        "../core/src/parser/vendors/aruba-aoscx.ts": {
          "bytesInOutput": 1684
        },
        "../core/src/parser/vendors/aruba-aosswitch.ts": {
          "bytesInOutput": 1226
        },
        "../core/src/parser/vendors/aruba-wlc.ts": {
          "bytesInOutput": 3365
        },
        "../core/src/parser/vendors/index.ts": {
          "bytesInOutput": 1730
        },
        "../core/src/parser/Sanitizer.ts": {
          "bytesInOutput": 402
        },
        "../core/src/constants.ts": {
          "bytesInOutput": 33
        },
        "../core/src/errors.ts": {
          "bytesInOutput": 412
        },
        "../core/src/parser/SchemaAwareParser.ts": {
          "bytesInOutput": 3262
        },
        "../core/src/parser/IncrementalParser.ts": {
          "bytesInOutput": 3788
        },
        "../core/src/engine/RuleExecutor.ts": {
          "bytesInOutput": 1997
        },
        "../core/src/engine/Runner.ts": {
          "bytesInOutput": 2151
        },
        "../rules-default/src/common/helpers.ts": {
          "bytesInOutput": 461
        },
        "../rules-default/src/common/network-rules.ts": {
          "bytesInOutput": 5228
        },
        "../rules-default/src/common/index.ts": {
          "bytesInOutput": 0
        },
        "../rules-default/src/index.ts": {
          "bytesInOutput": 239
        },
        "../rules-default/src/cisco/helpers.ts": {
          "bytesInOutput": 1703
        },
        "../rules-default/src/cisco/ios-rules.ts": {
          "bytesInOutput": 18733
        },
        "../rules-default/src/cisco/index.ts": {
          "bytesInOutput": 0
        },
        "../rules-default/src/juniper/helpers.ts": {
          "bytesInOutput": 1115
        },
        "../rules-default/src/juniper/junos-rules.ts": {
          "bytesInOutput": 8330
        },
        "../rules-default/src/juniper/index.ts": {
          "bytesInOutput": 0
        },
        "../rules-default/src/aruba/helpers.ts": {
          "bytesInOutput": 2652
        },
        "../rules-default/src/aruba/index.ts": {
          "bytesInOutput": 193
        },
        "../rules-default/src/aruba/common-rules.ts": {
          "bytesInOutput": 4601
        },
        "../rules-default/src/aruba/aoscx-rules.ts": {
          "bytesInOutput": 7674
        },
        "../rules-default/src/aruba/aosswitch-rules.ts": {
          "bytesInOutput": 5410
        },
        "../rules-default/src/aruba/wlc-rules.ts": {
          "bytesInOutput": 6661
        }
      },
      "bytes": 103739
    }
  }
}
